{"cameraMode":{"drawMode":0,"name":"Shaded","section":"Shading Mode"},"sceneLighting":true,"audioPlay":false,"sceneViewState":{"showFog":true,"showMaterialUpdate":false,"showSkybox":true,"showFlares":true,"showImageEffects":true,"showParticleSystems":true},"in2DMode":false,"pivot":{"x":-3.3541202545166017,"y":0.502039909362793,"z":-1.7740073204040528},"rotation":{"x":-0.3114248514175415,"y":0.4907369017601013,"z":-0.19334279000759126,"w":-0.7904495000839233},"size":18.09751319885254,"orthographic":false}